streams_explorer/__init__.py
streams_explorer/api/__init__.py
streams_explorer/api/dependencies/__init__.py
streams_explorer/api/dependencies/dataflow_graph.py
streams_explorer/api/dependencies/streams_explorer.py
streams_explorer/api/routes/__init__.py
streams_explorer/api/routes/api.py
streams_explorer/api/routes/graph.py
streams_explorer/api/routes/kubernetes_health.py
streams_explorer/api/routes/metrics.py
streams_explorer/api/routes/node.py
streams_explorer/api/routes/pipelines.py
streams_explorer/api/routes/update.py
streams_explorer/application.py
streams_explorer/core/__init__.py
streams_explorer/core/client_manager.py
streams_explorer/core/config.py
streams_explorer/core/extractor/__init__.py
streams_explorer/core/extractor/default/__init__.py
streams_explorer/core/extractor/default/elasticsearch_sink.py
streams_explorer/core/extractor/default/generic.py
streams_explorer/core/extractor/default/jdbc_sink.py
streams_explorer/core/extractor/default/redis_sink.py
streams_explorer/core/extractor/default/s3_sink.py
streams_explorer/core/extractor/default/streams_bootstrap_producer.py
streams_explorer/core/extractor/default/transformer.py
streams_explorer/core/extractor/extractor.py
streams_explorer/core/extractor/extractor_container.py
streams_explorer/core/k8s_app.py
streams_explorer/core/k8s_config_parser.py
streams_explorer/core/node_info_extractor.py
streams_explorer/core/services/__init__.py
streams_explorer/core/services/dataflow_graph.py
streams_explorer/core/services/kafka_admin_client.py
streams_explorer/core/services/kafkaconnect.py
streams_explorer/core/services/kubernetes.py
streams_explorer/core/services/linking_services.py
streams_explorer/core/services/metric_providers.py
streams_explorer/core/services/schemaregistry.py
streams_explorer/default.py
streams_explorer/defaultlinker.py
streams_explorer/extractors.py
streams_explorer/k8s_config_parser.py
streams_explorer/linker.py
streams_explorer/metric_provider.py
streams_explorer/models/__init__.py
streams_explorer-2.4.1.dist-info/WHEEL
streams_explorer-2.4.1.dist-info/METADATA
streams_explorer-2.4.1.dist-info/entry_points.txt
streams_explorer-2.4.1.dist-info/RECORD
