Metadata-Version: 2.1
Name: streams-explorer
Version: 2.4.1
Summary: Explore Data Pipelines in Apache Kafka.
Home-page: https://github.com/bakdata/streams-explorer
License: MIT
Keywords: kafka,kubernetes,stream-processing,monitoring,pipelines
Author: bakdata
Requires-Python: >=3.10,<4.0
Classifier: Intended Audience :: Developers
Classifier: License :: OSI Approved :: MIT License
Classifier: Programming Language :: Python
Classifier: Programming Language :: Python :: 3
Classifier: Programming Language :: Python :: 3.10
Classifier: Programming Language :: Python :: 3.11
Classifier: Programming Language :: Python :: 3
Classifier: Programming Language :: Python :: 3 :: Only
Classifier: Programming Language :: Python :: 3.10
Classifier: Topic :: Software Development
Classifier: Topic :: Software Development :: Libraries
Classifier: Topic :: Software Development :: Libraries :: Python Modules
Classifier: Typing :: Typed
Requires-Dist: cachetools (>=4.2.2,<5.0.0)
Requires-Dist: confluent-kafka (==2.4.0)
Requires-Dist: dynaconf (>=3.1.7,<4.0.0)
Requires-Dist: fastapi (>=0.103.1,<0.104.0)
Requires-Dist: fastapi-utils (>=0.2.1,<0.3.0)
Requires-Dist: httpx (>=0.23.1,<0.24.0)
Requires-Dist: kubernetes-asyncio (>=32.0.0,<33.0.0)
Requires-Dist: loguru (>=0.5.3,<0.6.0)
Requires-Dist: matplotlib (>=3.4.3,<4.0.0)
Requires-Dist: networkx (>=2.6.3,<3.0.0)
Requires-Dist: pydantic (>=1.9.1,<2.0.0)
Requires-Dist: pygraphviz (>=1.10,<2.0)
Requires-Dist: uvicorn[standard] (>=0.20.0,<0.21.0)
Project-URL: Bug Tracker, https://github.com/bakdata/streams-explorer/issues
Project-URL: Repository, https://github.com/bakdata/streams-explorer
